{
  "type": "FeatureCollection",
  "features": [
    {
      "type": "Feature",
      "geometry": {
        "type": "Point",
        "coordinates": [
          125.270833,
          6.9875
        ]
      },
      "properties": {
        "name": "Mount Apo",
        "elevation": 2954,
        "prominence": 2954,
        "town": [
          "Davao City",
          "Digos",
          "Kidapawan",
          "Sta. Cruz"
        ],
        "province": [
          "Cotabato",
          "Davao del Sur"
        ],
        "region": [
          "XI",
          "XII"
        ],
        "island_group": "Mindanao",
        "alt_names": "",
        "marker-color": "#2e9e4a",
        "marker-size": "medium",
        "marker-symbol": "mountain"
      }
    }
  ]
}
